{
    "name": "DSLA",
    "symbol": "DSLA",
    "contract": "0x3affcca64c2a6f4e3b6bd9c64cd2c969efd1ecbe",
    "decimals": 18,
    "logo": "https://etherscan.io/token/images/dsla_32.png?v=2",
    "desc": {
        "en": "ERC20",
        "zh": "ERC20"
    },
    "website": "",
    "whitepaper": "DSLA Protocol is a decentralized alternative to SLA contracts. It enables anyone to vouch for the reliability of a service, earn rewards when the service performs as expected, and claim financial compensation when the service doesn’t meet expectations.",
    "invalid": true,
    "links": {
        "twitter": "",
        "telegram": ""
    }
}