{
    "name": "Internxt",
    "symbol": "INXT",
    "contract": "0xa8006c4ca56f24d6836727d106349320db7fef82",
    "decimals": 8,
    "logo": "https://etherscan.io/token/images/internxt_32.png",
    "desc": {
        "en": "ERC20",
        "zh": "ERC20"
    },
    "website": "",
    "whitepaper": "Launched in 2017, Internxt is working on building a private Internet. Its first service, Internxt Drive, is a decentralized cloud storage service available for individuals and businesses.",
    "invalid": true,
    "links": {
        "twitter": "",
        "telegram": ""
    }
}