{
    "name": "Numeraire",
    "symbol": "NMR",
    "contract": "0x1776e1f26f98b1a5df9cd347953a26dd3cb46671",
    "decimals": 18,
    "logo": "https://assets.coingecko.com/coins/images/752/large/numeraire.png?1592538976",
    "desc": {
        "en": "ERC20",
        "zh": "ERC20"
    },
    "website": "",
    "whitepaper": "NMR is the scarcity token at the core of the Erasure Protocol. NMR cannot be minted and its core use is for staking and burning. The Erasure Protocol brings negative incentives to any website on the internet by providing users with economic skin in the game and punishing bad actors.",
    "invalid": true,
    "links": {
        "twitter": "",
        "telegram": ""
    }
}